{
    "school": "ABC School",
    "classes": [
      { "id":1,
        "class_name": "Class 1",
        "students": [
          {"ID": 1, "Name": "John Doe", "Grade": "A+", "Percentage": 92},
          {"ID": 2, "Name": "Jane Smith", "Grade": "A", "Percentage": 85},
          {"ID": 3, "Name": "Mike Johnson", "Grade": "A+", "Percentage": 94},
          {"ID": 4, "Name": "Emily Brown", "Grade": "A", "Percentage": 89},
          {"ID": 5, "Name": "Alex Turner", "Grade": "A+", "Percentage": 91},
          {"ID": 6, "Name": "Sophia Miller", "Grade": "A", "Percentage": 86},
          {"ID": 7, "Name": "David White", "Grade": "A", "Percentage": 88},
          {"ID": 8, "Name": "Emma Davis", "Grade": "A+", "Percentage": 93},
          {"ID": 9, "Name": "Robert Taylor", "Grade": "A", "Percentage": 87},
          {"ID": 10, "Name": "Olivia Johnson", "Grade": "A+", "Percentage": 95}
        ]
      },
      { "id":2,
        "class_name": "Class 2",
        "students": [
          {"ID": 11, "Name": "Daniel Brown", "Grade": "A", "Percentage": 88},
          {"ID": 12, "Name": "Sophie Wilson", "Grade": "A+", "Percentage": 94},
          {"ID": 13, "Name": "James Davis", "Grade": "A", "Percentage": 87},
          {"ID": 14, "Name": "Isabella Harris", "Grade": "A+", "Percentage": 96},
          {"ID": 15, "Name": "Andrew Miller", "Grade": "A", "Percentage": 89},
          {"ID": 16, "Name": "Ella Brown", "Grade": "A", "Percentage": 86},
          {"ID": 17, "Name": "Michael Turner", "Grade": "A+", "Percentage": 92},
          {"ID": 18, "Name": "Grace Martin", "Grade": "A", "Percentage": 85},
          {"ID": 19, "Name": "William White", "Grade": "A+", "Percentage": 91},
          {"ID": 20, "Name": "Ava Jackson", "Grade": "A", "Percentage": 88}
        ]
      }
    ]
  }
  